Metadata-Version: 2.1
Name: addcalculate
Version: 1.0
Summary: This is a calculate
Home-page: UNKNOWN
Author: Mengxin
License: UNKNOWN
Platform: UNKNOWN
